blmarkdown/App.py
blmarkdown/Learning.py
blmarkdown/LearningData.py
blmarkdown/Preview.py
blmarkdown/Utill.py
blmarkdown/__init__.py
blmarkdown-2.3.dist-info/LICENSE.txt
blmarkdown-2.3.dist-info/METADATA
blmarkdown-2.3.dist-info/WHEEL
blmarkdown-2.3.dist-info/top_level.txt
blmarkdown-2.3.dist-info/RECORD
