Metadata-Version: 2.1
Name: blmarkdown
Version: 2.3
Summary: Bear Au Jus Learning Markdown (blmarkdown) is a tool used to help you documenting your learning history in rich and flavored markdown.
Home-page: https://github.com/bearaujus/blmarkdown
Author: Bear Au Jus - ジュースとくま
Author-email: haryobagasasyafah6@gmail.com
License: MIT
Keywords: blmarkdown,bearaujus learning markdown,bearaujus markdown,bearaujus learning,bearaujus,learning,markdown,github learning history documentation using python,python,markdown generator,github,documenting learning history,github markdown,documenting python code,python code documentation generator
Platform: UNKNOWN
Classifier: Development Status :: 5 - Production/Stable
Classifier: Intended Audience :: Developers
Classifier: Operating System :: OS Independent
Classifier: License :: OSI Approved :: MIT License
Classifier: Programming Language :: Python :: 3.7
Classifier: Natural Language :: English
Classifier: Topic :: Utilities
License-File: LICENSE.txt
Requires-Dist: markdown
Requires-Dist: datetime
